<?xml version="1.0" encoding="windows-1252"?>
<XMI xmi.version="1.1" xmlns:UML="omg.org/UML1.3">
	<XMI.header>
		<XMI.documentation>
			<XMI.exporter>Enterprise Architect</XMI.exporter>
			<XMI.exporterVersion>2.5</XMI.exporterVersion>
		</XMI.documentation>
	</XMI.header>
	<XMI.content>
		<UML:Model name="EA Model" xmi.id="MX_EAID_F97D0EF0_0289_4921_B654_5FB641915D04">
			<UML:Namespace.ownedElement>
				<UML:Class name="EARootClass" xmi.id="EAID_11111111_5487_4080_A7F4_41526CB0AA00" isRoot="true" isLeaf="false" isAbstract="false"/>
				<UML:Package name="OGC" xmi.id="EAPK_F97D0EF0_0289_4921_B654_5FB641915D04" isRoot="false" isLeaf="false" isAbstract="false" visibility="public">
					<UML:ModelElement.taggedValue>
						<UML:TaggedValue tag="parent" value="EAPK_7B6B28E9_C583_4363_9E9C_F37A37AE06C9"/>
						<UML:TaggedValue tag="ea_package_id" value="6674"/>
						<UML:TaggedValue tag="created" value="2018-06-04 00:00:00"/>
						<UML:TaggedValue tag="modified" value="2018-06-04 00:00:00"/>
						<UML:TaggedValue tag="iscontrolled" value="TRUE"/>
						<UML:TaggedValue tag="xmlpath" value="ogc\OGC.xml"/>
						<UML:TaggedValue tag="version" value="1.0"/>
						<UML:TaggedValue tag="isprotected" value="FALSE"/>
						<UML:TaggedValue tag="usedtd" value="FALSE"/>
						<UML:TaggedValue tag="owner" value="knjetl"/>
						<UML:TaggedValue tag="xmiver" value="Enterprise Architect XMI/UML 1.3"/>
						<UML:TaggedValue tag="logxml" value="FALSE"/>
						<UML:TaggedValue tag="tpos" value="2"/>
						<UML:TaggedValue tag="packageFlags" value="isModel=1;VICON=3;Recurse=0;VCCFG=ISOTC211;CRC=0;"/>
						<UML:TaggedValue tag="batchsave" value="0"/>
						<UML:TaggedValue tag="batchload" value="0"/>
						<UML:TaggedValue tag="phase" value="1.0"/>
						<UML:TaggedValue tag="status" value="Proposed"/>
						<UML:TaggedValue tag="author" value="knjetl"/>
						<UML:TaggedValue tag="complexity" value="1"/>
						<UML:TaggedValue tag="ea_stype" value="Public"/>
						<UML:TaggedValue tag="tpos" value="2"/>
						<UML:TaggedValue tag="gentype" value="Java"/>
					</UML:ModelElement.taggedValue>
					<UML:Namespace.ownedElement>
						<UML:Collaboration xmi.id="EAID_F97D0EF0_0289_4921_B654_5FB641915D04_Collaboration" name="Collaborations">
							<UML:Namespace.ownedElement>
								<UML:ClassifierRole name="OGC Web Services Context Document (OWS Context)" xmi.id="EAID_7735B13A_D209_46d0_9D9B_4EF5E34B35E0" visibility="public" base="EAID_11111111_5487_4080_A7F4_41526CB0AA00">
									<UML:ModelElement.taggedValue>
										<UML:TaggedValue tag="isAbstract" value="false"/>
										<UML:TaggedValue tag="isSpecification" value="false"/>
										<UML:TaggedValue tag="ea_stype" value="Package"/>
										<UML:TaggedValue tag="ea_ntype" value="0"/>
										<UML:TaggedValue tag="version" value="1.0"/>
										<UML:TaggedValue tag="isActive" value="false"/>
										<UML:TaggedValue tag="package" value="EAPK_F97D0EF0_0289_4921_B654_5FB641915D04"/>
										<UML:TaggedValue tag="date_created" value="2018-06-04 11:44:46"/>
										<UML:TaggedValue tag="date_modified" value="2018-06-04 11:44:59"/>
										<UML:TaggedValue tag="gentype" value="Java"/>
										<UML:TaggedValue tag="tagged" value="0"/>
										<UML:TaggedValue tag="package2" value="EAID_7735B13A_D209_46d0_9D9B_4EF5E34B35E0"/>
										<UML:TaggedValue tag="package_name" value="OGC"/>
										<UML:TaggedValue tag="phase" value="1.0"/>
										<UML:TaggedValue tag="author" value="knjetl"/>
										<UML:TaggedValue tag="complexity" value="1"/>
										<UML:TaggedValue tag="status" value="Proposed"/>
										<UML:TaggedValue tag="tpos" value="0"/>
										<UML:TaggedValue tag="ea_localid" value="6675"/>
										<UML:TaggedValue tag="ea_eleType" value="package"/>
										<UML:TaggedValue tag="style" value="BackColor=-1;BorderColor=-1;BorderWidth=-1;FontColor=-1;VSwimLanes=1;HSwimLanes=1;BorderStyle=0;"/>
									</UML:ModelElement.taggedValue>
								</UML:ClassifierRole>
							</UML:Namespace.ownedElement>
							<UML:Collaboration.interaction/>
						</UML:Collaboration>
						<UML:Package name="OGC Web Services Context Document (OWS Context)" xmi.id="EAPK_7735B13A_D209_46d0_9D9B_4EF5E34B35E0" isRoot="false" isLeaf="false" isAbstract="false" visibility="public">
							<UML:ModelElement.taggedValue>
								<UML:TaggedValue tag="parent" value="EAPK_F97D0EF0_0289_4921_B654_5FB641915D04"/>
								<UML:TaggedValue tag="created" value="2018-06-04 11:44:46"/>
								<UML:TaggedValue tag="modified" value="2018-06-04 11:44:59"/>
								<UML:TaggedValue tag="iscontrolled" value="TRUE"/>
								<UML:TaggedValue tag="xmlpath" value="ogc\OWS Context\Trunk\OGC Web Services Context Document (OWS Context).xml"/>
								<UML:TaggedValue tag="version" value="1.0"/>
								<UML:TaggedValue tag="isprotected" value="FALSE"/>
								<UML:TaggedValue tag="usedtd" value="FALSE"/>
								<UML:TaggedValue tag="owner" value="knjetl"/>
								<UML:TaggedValue tag="xmiver" value="Enterprise Architect XMI/UML 1.3"/>
								<UML:TaggedValue tag="logxml" value="FALSE"/>
								<UML:TaggedValue tag="batchsave" value="0"/>
								<UML:TaggedValue tag="batchload" value="0"/>
								<UML:TaggedValue tag="packageFlags" value="Recurse=0;VCCFG=ISOTC211;"/>
								<UML:TaggedValue tag="savedasstub" value="true"/>
								<UML:TaggedValue tag="phase" value="1.0"/>
								<UML:TaggedValue tag="status" value="Proposed"/>
								<UML:TaggedValue tag="author" value="knjetl"/>
								<UML:TaggedValue tag="complexity" value="1"/>
								<UML:TaggedValue tag="ea_stype" value="Public"/>
							</UML:ModelElement.taggedValue>
						</UML:Package>
					</UML:Namespace.ownedElement>
				</UML:Package>
			</UML:Namespace.ownedElement>
		</UML:Model>
	</XMI.content>
	<XMI.difference/>
	<XMI.extensions xmi.extender="Enterprise Architect 2.5"/>
</XMI>
