<?xml version="1.0" encoding="windows-1252"?>
<XMI xmi.version="1.1" xmlns:UML="omg.org/UML1.3">
	<XMI.header>
		<XMI.documentation>
			<XMI.exporter>Enterprise Architect</XMI.exporter>
			<XMI.exporterVersion>2.5</XMI.exporterVersion>
		</XMI.documentation>
	</XMI.header>
	<XMI.content>
		<UML:Model name="EA Model" xmi.id="MX_EAID_2184D109_9F23_4b03_863B_F722FFFF9D9A">
			<UML:Namespace.ownedElement>
				<UML:Class name="EARootClass" xmi.id="EAID_11111111_5487_4080_A7F4_41526CB0AA00" isRoot="true" isLeaf="false" isAbstract="false"/>
				<UML:Package name="ISO 19103 Conceptual schema language XML" xmi.id="EAPK_2184D109_9F23_4b03_863B_F722FFFF9D9A" isRoot="false" isLeaf="false" isAbstract="false" visibility="public">
					<UML:ModelElement.taggedValue>
						<UML:TaggedValue tag="parent" value="EAPK_A6AEEF28_5309_41bc_8024_9634FFD7CC7E"/>
						<UML:TaggedValue tag="created" value="2017-08-04 09:29:21"/>
						<UML:TaggedValue tag="modified" value="2017-08-04 09:36:08"/>
						<UML:TaggedValue tag="iscontrolled" value="TRUE"/>
						<UML:TaggedValue tag="xmlpath" value="iso-19103\tags\ISO 19103 Conceptual schema language XML.xml"/>
						<UML:TaggedValue tag="lastloaddate" value="2017-08-04 09:43:55"/>
						<UML:TaggedValue tag="lastsavedate" value="2017-08-04 09:36:02"/>
						<UML:TaggedValue tag="version" value="1.0"/>
						<UML:TaggedValue tag="isprotected" value="FALSE"/>
						<UML:TaggedValue tag="usedtd" value="FALSE"/>
						<UML:TaggedValue tag="owner" value="knjetl"/>
						<UML:TaggedValue tag="xmiver" value="Enterprise Architect XMI/UML 1.3"/>
						<UML:TaggedValue tag="logxml" value="FALSE"/>
						<UML:TaggedValue tag="packageFlags" value="Recurse=0;VCCFG=implementation-XML;CRC=0;"/>
						<UML:TaggedValue tag="batchsave" value="0"/>
						<UML:TaggedValue tag="batchload" value="0"/>
						<UML:TaggedValue tag="phase" value="1.0"/>
						<UML:TaggedValue tag="status" value="Proposed"/>
						<UML:TaggedValue tag="author" value="knjetl"/>
						<UML:TaggedValue tag="complexity" value="1"/>
						<UML:TaggedValue tag="ea_stype" value="Public"/>
						<UML:TaggedValue tag="tpos" value="0"/>
						<UML:TaggedValue tag="gentype" value="Java"/>
					</UML:ModelElement.taggedValue>
					<UML:Namespace.ownedElement>
						<UML:Collaboration xmi.id="EAID_2184D109_9F23_4b03_863B_F722FFFF9D9A_Collaboration" name="Collaborations">
							<UML:Namespace.ownedElement>
								<UML:ClassifierRole name="ISO TS19103 Edition 1 XML" xmi.id="EAID_31591D82_13F0_4687_BC11_BEDFBCEB9772" visibility="public" base="EAID_11111111_5487_4080_A7F4_41526CB0AA00">
									<UML:ModelElement.taggedValue>
										<UML:TaggedValue tag="documentation" value="import from Harmonized model with strip GUIDS 2014-07-10"/>
										<UML:TaggedValue tag="isAbstract" value="false"/>
										<UML:TaggedValue tag="isSpecification" value="false"/>
										<UML:TaggedValue tag="ea_stype" value="Package"/>
										<UML:TaggedValue tag="ea_ntype" value="0"/>
										<UML:TaggedValue tag="version" value="1.0."/>
										<UML:TaggedValue tag="isActive" value="false"/>
										<UML:TaggedValue tag="package" value="EAPK_2184D109_9F23_4b03_863B_F722FFFF9D9A"/>
										<UML:TaggedValue tag="date_created" value="2008-04-17 08:46:36"/>
										<UML:TaggedValue tag="date_modified" value="2017-08-04 09:48:30"/>
										<UML:TaggedValue tag="gentype" value="&lt;none&gt;"/>
										<UML:TaggedValue tag="tagged" value="0"/>
										<UML:TaggedValue tag="package2" value="EAID_31591D82_13F0_4687_BC11_BEDFBCEB9772"/>
										<UML:TaggedValue tag="package_name" value="ISO 19103 Conceptual schema language XML"/>
										<UML:TaggedValue tag="alias" value="Conceptual schema language"/>
										<UML:TaggedValue tag="complexity" value="1"/>
										<UML:TaggedValue tag="tpos" value="2"/>
										<UML:TaggedValue tag="ea_localid" value="4555"/>
										<UML:TaggedValue tag="ea_eleType" value="package"/>
										<UML:TaggedValue tag="style" value="BackColor=-1;BorderColor=-1;BorderWidth=-1;FontColor=-1;VSwimLanes=1;HSwimLanes=1;BorderStyle=0;"/>
									</UML:ModelElement.taggedValue>
								</UML:ClassifierRole>
								<UML:ClassifierRole name="ISO 19103 Edition 1 XML" xmi.id="EAID_8339FE1D_E6C1_430f_87EA_D3EB217A11EC" visibility="public" base="EAID_11111111_5487_4080_A7F4_41526CB0AA00">
									<UML:ModelElement.taggedValue>
										<UML:TaggedValue tag="isAbstract" value="false"/>
										<UML:TaggedValue tag="isSpecification" value="false"/>
										<UML:TaggedValue tag="ea_stype" value="Package"/>
										<UML:TaggedValue tag="ea_ntype" value="0"/>
										<UML:TaggedValue tag="version" value="2015"/>
										<UML:TaggedValue tag="isActive" value="false"/>
										<UML:TaggedValue tag="package" value="EAPK_2184D109_9F23_4b03_863B_F722FFFF9D9A"/>
										<UML:TaggedValue tag="date_created" value="2015-04-22 11:41:07"/>
										<UML:TaggedValue tag="date_modified" value="2017-08-04 09:47:13"/>
										<UML:TaggedValue tag="gentype" value="Java"/>
										<UML:TaggedValue tag="tagged" value="0"/>
										<UML:TaggedValue tag="package2" value="EAID_8339FE1D_E6C1_430f_87EA_D3EB217A11EC"/>
										<UML:TaggedValue tag="package_name" value="ISO 19103 Conceptual schema language XML"/>
										<UML:TaggedValue tag="phase" value="1.0"/>
										<UML:TaggedValue tag="alias" value="Conceptual schema language"/>
										<UML:TaggedValue tag="author" value="John"/>
										<UML:TaggedValue tag="complexity" value="1"/>
										<UML:TaggedValue tag="status" value="Implemented"/>
										<UML:TaggedValue tag="tpos" value="1"/>
										<UML:TaggedValue tag="ea_localid" value="4570"/>
										<UML:TaggedValue tag="ea_eleType" value="package"/>
										<UML:TaggedValue tag="style" value="BackColor=-1;BorderColor=-1;BorderWidth=-1;FontColor=-1;VSwimLanes=1;HSwimLanes=1;BorderStyle=0;"/>
									</UML:ModelElement.taggedValue>
								</UML:ClassifierRole>
							</UML:Namespace.ownedElement>
							<UML:Collaboration.interaction/>
						</UML:Collaboration>
						<UML:Dependency client="EAPK_DC9F3A84_5D39_4092_AADF_860E89E61B89" supplier="EAPK_31591D82_13F0_4687_BC11_BEDFBCEB9772" xmi.id="EAID_04AA1765_B582_4465_ADFA_6793F4F08837" visibility="public">
							<UML:ModelElement.stereotype>
								<UML:Stereotype name="import"/>
							</UML:ModelElement.stereotype>
							<UML:ModelElement.taggedValue>
								<UML:TaggedValue tag="documentation" value="Created by HollowWorld Plugin"/>
								<UML:TaggedValue tag="style" value="3"/>
								<UML:TaggedValue tag="ea_type" value="Dependency"/>
								<UML:TaggedValue tag="direction" value="Source -&gt; Destination"/>
								<UML:TaggedValue tag="linemode" value="3"/>
								<UML:TaggedValue tag="linecolor" value="-1"/>
								<UML:TaggedValue tag="linewidth" value="0"/>
								<UML:TaggedValue tag="seqno" value="0"/>
								<UML:TaggedValue tag="stereotype" value="import"/>
								<UML:TaggedValue tag="headStyle" value="0"/>
								<UML:TaggedValue tag="lineStyle" value="0"/>
								<UML:TaggedValue tag="conditional" value=" &#xA;쳃mport"/>
								<UML:TaggedValue tag="ea_localid" value="59289"/>
								<UML:TaggedValue tag="ea_sourceName" value="Metadata Common Classes"/>
								<UML:TaggedValue tag="ea_targetName" value="ISO TS19103 Edition 1 XML"/>
								<UML:TaggedValue tag="ea_sourceType" value="Package"/>
								<UML:TaggedValue tag="ea_targetType" value="Package"/>
								<UML:TaggedValue tag="ea_sourceID" value="39761"/>
								<UML:TaggedValue tag="ea_targetID" value="39435"/>
								<UML:TaggedValue tag="src_visibility" value="Public"/>
								<UML:TaggedValue tag="src_aggregation" value="0"/>
								<UML:TaggedValue tag="src_isOrdered" value="false"/>
								<UML:TaggedValue tag="src_isNavigable" value="false"/>
								<UML:TaggedValue tag="src_style" value="Owned=0;Navigable=Non-Navigable;"/>
								<UML:TaggedValue tag="dst_visibility" value="Public"/>
								<UML:TaggedValue tag="dst_aggregation" value="0"/>
								<UML:TaggedValue tag="dst_isOrdered" value="false"/>
								<UML:TaggedValue tag="dst_isNavigable" value="false"/>
								<UML:TaggedValue tag="dst_style" value="Owned=0;Navigable=Navigable;"/>
								<UML:TaggedValue tag="virtualInheritance" value="0"/>
								<UML:TaggedValue tag="mb" value=" &#xA;쳃mport"/>
							</UML:ModelElement.taggedValue>
						</UML:Dependency>
						<UML:Dependency client="EAPK_19EE7D8E_DC0C_42d9_B272_E478A5F95291" supplier="EAPK_31591D82_13F0_4687_BC11_BEDFBCEB9772" xmi.id="EAID_5D8F12B3_5393_4b04_A635_23493F611ADC" visibility="public">
							<UML:ModelElement.stereotype>
								<UML:Stereotype name="import"/>
							</UML:ModelElement.stereotype>
							<UML:ModelElement.taggedValue>
								<UML:TaggedValue tag="documentation" value="Created by HollowWorld Plugin"/>
								<UML:TaggedValue tag="style" value="3"/>
								<UML:TaggedValue tag="ea_type" value="Dependency"/>
								<UML:TaggedValue tag="direction" value="Source -&gt; Destination"/>
								<UML:TaggedValue tag="linemode" value="3"/>
								<UML:TaggedValue tag="linecolor" value="-1"/>
								<UML:TaggedValue tag="linewidth" value="0"/>
								<UML:TaggedValue tag="seqno" value="0"/>
								<UML:TaggedValue tag="stereotype" value="import"/>
								<UML:TaggedValue tag="headStyle" value="0"/>
								<UML:TaggedValue tag="lineStyle" value="0"/>
								<UML:TaggedValue tag="conditional" value=" &#xA;쳃mport"/>
								<UML:TaggedValue tag="ea_localid" value="59359"/>
								<UML:TaggedValue tag="ea_sourceName" value="Metadata base"/>
								<UML:TaggedValue tag="ea_targetName" value="ISO TS19103 Edition 1 XML"/>
								<UML:TaggedValue tag="ea_sourceType" value="Package"/>
								<UML:TaggedValue tag="ea_targetType" value="Package"/>
								<UML:TaggedValue tag="ea_sourceID" value="39742"/>
								<UML:TaggedValue tag="ea_targetID" value="39435"/>
								<UML:TaggedValue tag="src_visibility" value="Public"/>
								<UML:TaggedValue tag="src_aggregation" value="0"/>
								<UML:TaggedValue tag="src_isOrdered" value="false"/>
								<UML:TaggedValue tag="src_isNavigable" value="false"/>
								<UML:TaggedValue tag="src_style" value="Owned=0;Navigable=Non-Navigable;"/>
								<UML:TaggedValue tag="dst_visibility" value="Public"/>
								<UML:TaggedValue tag="dst_aggregation" value="0"/>
								<UML:TaggedValue tag="dst_isOrdered" value="false"/>
								<UML:TaggedValue tag="dst_isNavigable" value="false"/>
								<UML:TaggedValue tag="dst_style" value="Owned=0;Navigable=Navigable;"/>
								<UML:TaggedValue tag="virtualInheritance" value="0"/>
								<UML:TaggedValue tag="mb" value=" &#xA;쳃mport"/>
							</UML:ModelElement.taggedValue>
						</UML:Dependency>
						<UML:Dependency client="EAPK_CC8F3DBB_4765_419f_BDEF_7080D866A3E8" supplier="EAPK_31591D82_13F0_4687_BC11_BEDFBCEB9772" xmi.id="EAID_6546CD33_9C54_4d57_9876_040519502525" visibility="public">
							<UML:ModelElement.stereotype>
								<UML:Stereotype name="import"/>
							</UML:ModelElement.stereotype>
							<UML:ModelElement.taggedValue>
								<UML:TaggedValue tag="documentation" value="Created by HollowWorld Plugin"/>
								<UML:TaggedValue tag="style" value="3"/>
								<UML:TaggedValue tag="ea_type" value="Dependency"/>
								<UML:TaggedValue tag="direction" value="Source -&gt; Destination"/>
								<UML:TaggedValue tag="linemode" value="3"/>
								<UML:TaggedValue tag="linecolor" value="-1"/>
								<UML:TaggedValue tag="linewidth" value="0"/>
								<UML:TaggedValue tag="seqno" value="0"/>
								<UML:TaggedValue tag="stereotype" value="import"/>
								<UML:TaggedValue tag="headStyle" value="0"/>
								<UML:TaggedValue tag="lineStyle" value="0"/>
								<UML:TaggedValue tag="conditional" value=" &#xA;쳃mport"/>
								<UML:TaggedValue tag="ea_localid" value="59292"/>
								<UML:TaggedValue tag="ea_sourceName" value="Metadata for Distribution"/>
								<UML:TaggedValue tag="ea_targetName" value="ISO TS19103 Edition 1 XML"/>
								<UML:TaggedValue tag="ea_sourceType" value="Package"/>
								<UML:TaggedValue tag="ea_targetType" value="Package"/>
								<UML:TaggedValue tag="ea_sourceID" value="39760"/>
								<UML:TaggedValue tag="ea_targetID" value="39435"/>
								<UML:TaggedValue tag="src_visibility" value="Public"/>
								<UML:TaggedValue tag="src_aggregation" value="0"/>
								<UML:TaggedValue tag="src_isOrdered" value="false"/>
								<UML:TaggedValue tag="src_isNavigable" value="false"/>
								<UML:TaggedValue tag="src_style" value="Owned=0;Navigable=Non-Navigable;"/>
								<UML:TaggedValue tag="dst_visibility" value="Public"/>
								<UML:TaggedValue tag="dst_aggregation" value="0"/>
								<UML:TaggedValue tag="dst_isOrdered" value="false"/>
								<UML:TaggedValue tag="dst_isNavigable" value="false"/>
								<UML:TaggedValue tag="dst_style" value="Owned=0;Navigable=Navigable;"/>
								<UML:TaggedValue tag="virtualInheritance" value="0"/>
								<UML:TaggedValue tag="mb" value=" &#xA;쳃mport"/>
							</UML:ModelElement.taggedValue>
						</UML:Dependency>
						<UML:Dependency client="EAPK_9A048FF7_4C59_44aa_BABE_1B180DE058AF" supplier="EAPK_31591D82_13F0_4687_BC11_BEDFBCEB9772" xmi.id="EAID_8EB4947D_8170_4518_9BA4_5BC1F563FF7E" visibility="public">
							<UML:ModelElement.stereotype>
								<UML:Stereotype name="import"/>
							</UML:ModelElement.stereotype>
							<UML:ModelElement.taggedValue>
								<UML:TaggedValue tag="documentation" value="Created by HollowWorld Plugin"/>
								<UML:TaggedValue tag="style" value="3"/>
								<UML:TaggedValue tag="ea_type" value="Dependency"/>
								<UML:TaggedValue tag="direction" value="Source -&gt; Destination"/>
								<UML:TaggedValue tag="linemode" value="3"/>
								<UML:TaggedValue tag="linecolor" value="-1"/>
								<UML:TaggedValue tag="linewidth" value="0"/>
								<UML:TaggedValue tag="seqno" value="0"/>
								<UML:TaggedValue tag="stereotype" value="import"/>
								<UML:TaggedValue tag="headStyle" value="0"/>
								<UML:TaggedValue tag="lineStyle" value="0"/>
								<UML:TaggedValue tag="conditional" value=" &#xA;쳃mport"/>
								<UML:TaggedValue tag="ea_localid" value="60098"/>
								<UML:TaggedValue tag="ea_sourceName" value="Procedures for registration"/>
								<UML:TaggedValue tag="ea_targetName" value="ISO TS19103 Edition 1 XML"/>
								<UML:TaggedValue tag="ea_sourceType" value="Package"/>
								<UML:TaggedValue tag="ea_targetType" value="Package"/>
								<UML:TaggedValue tag="ea_sourceID" value="40640"/>
								<UML:TaggedValue tag="ea_targetID" value="39435"/>
								<UML:TaggedValue tag="src_visibility" value="Public"/>
								<UML:TaggedValue tag="src_aggregation" value="0"/>
								<UML:TaggedValue tag="src_isOrdered" value="false"/>
								<UML:TaggedValue tag="src_isNavigable" value="false"/>
								<UML:TaggedValue tag="src_style" value="Owned=0;Navigable=Non-Navigable;"/>
								<UML:TaggedValue tag="dst_visibility" value="Public"/>
								<UML:TaggedValue tag="dst_aggregation" value="0"/>
								<UML:TaggedValue tag="dst_isOrdered" value="false"/>
								<UML:TaggedValue tag="dst_isNavigable" value="false"/>
								<UML:TaggedValue tag="dst_style" value="Owned=0;Navigable=Navigable;"/>
								<UML:TaggedValue tag="virtualInheritance" value="0"/>
								<UML:TaggedValue tag="mb" value=" &#xA;쳃mport"/>
							</UML:ModelElement.taggedValue>
						</UML:Dependency>
						<UML:Dependency client="EAPK_A1EEA4B8_12F2_434d_BAEF_3C6AA7800EDD" supplier="EAPK_31591D82_13F0_4687_BC11_BEDFBCEB9772" xmi.id="EAID_9F27D3AB_B280_4adc_9910_63120BEB676E" visibility="public">
							<UML:ModelElement.stereotype>
								<UML:Stereotype name="import"/>
							</UML:ModelElement.stereotype>
							<UML:ModelElement.taggedValue>
								<UML:TaggedValue tag="documentation" value="Created by HollowWorld Plugin"/>
								<UML:TaggedValue tag="style" value="3"/>
								<UML:TaggedValue tag="ea_type" value="Dependency"/>
								<UML:TaggedValue tag="direction" value="Source -&gt; Destination"/>
								<UML:TaggedValue tag="linemode" value="3"/>
								<UML:TaggedValue tag="linecolor" value="-1"/>
								<UML:TaggedValue tag="linewidth" value="0"/>
								<UML:TaggedValue tag="seqno" value="0"/>
								<UML:TaggedValue tag="stereotype" value="import"/>
								<UML:TaggedValue tag="headStyle" value="0"/>
								<UML:TaggedValue tag="lineStyle" value="0"/>
								<UML:TaggedValue tag="conditional" value=" &#xA;쳃mport"/>
								<UML:TaggedValue tag="ea_localid" value="59993"/>
								<UML:TaggedValue tag="ea_sourceName" value="Data quality"/>
								<UML:TaggedValue tag="ea_targetName" value="ISO TS19103 Edition 1 XML"/>
								<UML:TaggedValue tag="ea_sourceType" value="Package"/>
								<UML:TaggedValue tag="ea_targetType" value="Package"/>
								<UML:TaggedValue tag="ea_sourceID" value="40471"/>
								<UML:TaggedValue tag="ea_targetID" value="39435"/>
								<UML:TaggedValue tag="src_visibility" value="Public"/>
								<UML:TaggedValue tag="src_aggregation" value="0"/>
								<UML:TaggedValue tag="src_isOrdered" value="false"/>
								<UML:TaggedValue tag="src_isNavigable" value="false"/>
								<UML:TaggedValue tag="src_style" value="Owned=0;Navigable=Non-Navigable;"/>
								<UML:TaggedValue tag="dst_visibility" value="Public"/>
								<UML:TaggedValue tag="dst_aggregation" value="0"/>
								<UML:TaggedValue tag="dst_isOrdered" value="false"/>
								<UML:TaggedValue tag="dst_isNavigable" value="false"/>
								<UML:TaggedValue tag="dst_style" value="Owned=0;Navigable=Navigable;"/>
								<UML:TaggedValue tag="virtualInheritance" value="0"/>
								<UML:TaggedValue tag="mb" value=" &#xA;쳃mport"/>
							</UML:ModelElement.taggedValue>
						</UML:Dependency>
						<UML:Dependency client="EAPK_757D8C16_2C34_47c8_B7A5_FC55871A4D53" supplier="EAPK_31591D82_13F0_4687_BC11_BEDFBCEB9772" xmi.id="EAID_AD51F969_76E8_4f7c_A46D_C3B2C48A0EA6" visibility="public">
							<UML:ModelElement.stereotype>
								<UML:Stereotype name="import"/>
							</UML:ModelElement.stereotype>
							<UML:ModelElement.taggedValue>
								<UML:TaggedValue tag="documentation" value="Created by HollowWorld Plugin"/>
								<UML:TaggedValue tag="style" value="3"/>
								<UML:TaggedValue tag="ea_type" value="Dependency"/>
								<UML:TaggedValue tag="direction" value="Source -&gt; Destination"/>
								<UML:TaggedValue tag="linemode" value="3"/>
								<UML:TaggedValue tag="linecolor" value="-1"/>
								<UML:TaggedValue tag="linewidth" value="0"/>
								<UML:TaggedValue tag="seqno" value="0"/>
								<UML:TaggedValue tag="stereotype" value="import"/>
								<UML:TaggedValue tag="headStyle" value="0"/>
								<UML:TaggedValue tag="lineStyle" value="0"/>
								<UML:TaggedValue tag="conditional" value=" &#xA;쳃mport"/>
								<UML:TaggedValue tag="ea_localid" value="60277"/>
								<UML:TaggedValue tag="ea_sourceName" value="Feature Catalogue"/>
								<UML:TaggedValue tag="ea_targetName" value="ISO TS19103 Edition 1 XML"/>
								<UML:TaggedValue tag="ea_sourceType" value="Package"/>
								<UML:TaggedValue tag="ea_targetType" value="Package"/>
								<UML:TaggedValue tag="ea_sourceID" value="40775"/>
								<UML:TaggedValue tag="ea_targetID" value="39435"/>
								<UML:TaggedValue tag="src_visibility" value="Public"/>
								<UML:TaggedValue tag="src_aggregation" value="0"/>
								<UML:TaggedValue tag="src_isOrdered" value="false"/>
								<UML:TaggedValue tag="src_isNavigable" value="false"/>
								<UML:TaggedValue tag="src_style" value="Owned=0;Navigable=Non-Navigable;"/>
								<UML:TaggedValue tag="dst_visibility" value="Public"/>
								<UML:TaggedValue tag="dst_aggregation" value="0"/>
								<UML:TaggedValue tag="dst_isOrdered" value="false"/>
								<UML:TaggedValue tag="dst_isNavigable" value="false"/>
								<UML:TaggedValue tag="dst_style" value="Owned=0;Navigable=Navigable;"/>
								<UML:TaggedValue tag="virtualInheritance" value="0"/>
								<UML:TaggedValue tag="mb" value=" &#xA;쳃mport"/>
							</UML:ModelElement.taggedValue>
						</UML:Dependency>
						<UML:Dependency client="EAPK_5AC9C40D_B36F_4a1b_B66C_BBA035747259" supplier="EAPK_31591D82_13F0_4687_BC11_BEDFBCEB9772" xmi.id="EAID_AD5DBBA9_BB64_4016_B091_DBF7CEA65AEB" visibility="public">
							<UML:ModelElement.stereotype>
								<UML:Stereotype name="import"/>
							</UML:ModelElement.stereotype>
							<UML:ModelElement.taggedValue>
								<UML:TaggedValue tag="documentation" value="Created by HollowWorld Plugin"/>
								<UML:TaggedValue tag="style" value="3"/>
								<UML:TaggedValue tag="ea_type" value="Dependency"/>
								<UML:TaggedValue tag="direction" value="Source -&gt; Destination"/>
								<UML:TaggedValue tag="linemode" value="3"/>
								<UML:TaggedValue tag="linecolor" value="-1"/>
								<UML:TaggedValue tag="linewidth" value="0"/>
								<UML:TaggedValue tag="seqno" value="0"/>
								<UML:TaggedValue tag="stereotype" value="import"/>
								<UML:TaggedValue tag="headStyle" value="0"/>
								<UML:TaggedValue tag="lineStyle" value="0"/>
								<UML:TaggedValue tag="conditional" value=" &#xA;쳃mport"/>
								<UML:TaggedValue tag="ea_localid" value="59318"/>
								<UML:TaggedValue tag="ea_sourceName" value="Metadata for Acquisition"/>
								<UML:TaggedValue tag="ea_targetName" value="ISO TS19103 Edition 1 XML"/>
								<UML:TaggedValue tag="ea_sourceType" value="Package"/>
								<UML:TaggedValue tag="ea_targetType" value="Package"/>
								<UML:TaggedValue tag="ea_sourceID" value="39751"/>
								<UML:TaggedValue tag="ea_targetID" value="39435"/>
								<UML:TaggedValue tag="src_visibility" value="Public"/>
								<UML:TaggedValue tag="src_aggregation" value="0"/>
								<UML:TaggedValue tag="src_isOrdered" value="false"/>
								<UML:TaggedValue tag="src_isNavigable" value="false"/>
								<UML:TaggedValue tag="src_style" value="Owned=0;Navigable=Non-Navigable;"/>
								<UML:TaggedValue tag="dst_visibility" value="Public"/>
								<UML:TaggedValue tag="dst_aggregation" value="0"/>
								<UML:TaggedValue tag="dst_isOrdered" value="false"/>
								<UML:TaggedValue tag="dst_isNavigable" value="false"/>
								<UML:TaggedValue tag="dst_style" value="Owned=0;Navigable=Navigable;"/>
								<UML:TaggedValue tag="virtualInheritance" value="0"/>
								<UML:TaggedValue tag="mb" value=" &#xA;쳃mport"/>
							</UML:ModelElement.taggedValue>
						</UML:Dependency>
						<UML:Dependency client="EAPK_9CADA801_6694_4944_90FB_93A9CB976661" supplier="EAPK_31591D82_13F0_4687_BC11_BEDFBCEB9772" xmi.id="EAID_B0B44AAD_BA64_4e97_A7F1_5357A5B696A4" visibility="public">
							<UML:ModelElement.stereotype>
								<UML:Stereotype name="import"/>
							</UML:ModelElement.stereotype>
							<UML:ModelElement.taggedValue>
								<UML:TaggedValue tag="documentation" value="Created by HollowWorld Plugin"/>
								<UML:TaggedValue tag="style" value="3"/>
								<UML:TaggedValue tag="ea_type" value="Dependency"/>
								<UML:TaggedValue tag="direction" value="Source -&gt; Destination"/>
								<UML:TaggedValue tag="linemode" value="3"/>
								<UML:TaggedValue tag="linecolor" value="-1"/>
								<UML:TaggedValue tag="linewidth" value="0"/>
								<UML:TaggedValue tag="seqno" value="0"/>
								<UML:TaggedValue tag="stereotype" value="import"/>
								<UML:TaggedValue tag="headStyle" value="0"/>
								<UML:TaggedValue tag="lineStyle" value="0"/>
								<UML:TaggedValue tag="conditional" value=" &#xA;쳃mport"/>
								<UML:TaggedValue tag="ea_localid" value="59297"/>
								<UML:TaggedValue tag="ea_sourceName" value="Metadata for Lineage"/>
								<UML:TaggedValue tag="ea_targetName" value="ISO TS19103 Edition 1 XML"/>
								<UML:TaggedValue tag="ea_sourceType" value="Package"/>
								<UML:TaggedValue tag="ea_targetType" value="Package"/>
								<UML:TaggedValue tag="ea_sourceID" value="39758"/>
								<UML:TaggedValue tag="ea_targetID" value="39435"/>
								<UML:TaggedValue tag="src_visibility" value="Public"/>
								<UML:TaggedValue tag="src_aggregation" value="0"/>
								<UML:TaggedValue tag="src_isOrdered" value="false"/>
								<UML:TaggedValue tag="src_isNavigable" value="false"/>
								<UML:TaggedValue tag="src_style" value="Owned=0;Navigable=Non-Navigable;"/>
								<UML:TaggedValue tag="dst_visibility" value="Public"/>
								<UML:TaggedValue tag="dst_aggregation" value="0"/>
								<UML:TaggedValue tag="dst_isOrdered" value="false"/>
								<UML:TaggedValue tag="dst_isNavigable" value="false"/>
								<UML:TaggedValue tag="dst_style" value="Owned=0;Navigable=Navigable;"/>
								<UML:TaggedValue tag="virtualInheritance" value="0"/>
								<UML:TaggedValue tag="mb" value=" &#xA;쳃mport"/>
							</UML:ModelElement.taggedValue>
						</UML:Dependency>
						<UML:Dependency client="EAPK_1D0C3864_B566_447c_A51E_52AE73A7737D" supplier="EAPK_31591D82_13F0_4687_BC11_BEDFBCEB9772" xmi.id="EAID_C6BAA895_7390_42f4_85BE_ED73833A87F0" visibility="public">
							<UML:ModelElement.stereotype>
								<UML:Stereotype name="import"/>
							</UML:ModelElement.stereotype>
							<UML:ModelElement.taggedValue>
								<UML:TaggedValue tag="documentation" value="Created by HollowWorld Plugin"/>
								<UML:TaggedValue tag="style" value="3"/>
								<UML:TaggedValue tag="ea_type" value="Dependency"/>
								<UML:TaggedValue tag="direction" value="Source -&gt; Destination"/>
								<UML:TaggedValue tag="linemode" value="3"/>
								<UML:TaggedValue tag="linecolor" value="-1"/>
								<UML:TaggedValue tag="linewidth" value="0"/>
								<UML:TaggedValue tag="seqno" value="0"/>
								<UML:TaggedValue tag="stereotype" value="import"/>
								<UML:TaggedValue tag="headStyle" value="0"/>
								<UML:TaggedValue tag="lineStyle" value="0"/>
								<UML:TaggedValue tag="conditional" value=" &#xA;쳃mport"/>
								<UML:TaggedValue tag="ea_localid" value="59346"/>
								<UML:TaggedValue tag="ea_sourceName" value="Metadata for Constraints"/>
								<UML:TaggedValue tag="ea_targetName" value="ISO TS19103 Edition 1 XML"/>
								<UML:TaggedValue tag="ea_sourceType" value="Package"/>
								<UML:TaggedValue tag="ea_targetType" value="Package"/>
								<UML:TaggedValue tag="ea_sourceID" value="39744"/>
								<UML:TaggedValue tag="ea_targetID" value="39435"/>
								<UML:TaggedValue tag="src_visibility" value="Public"/>
								<UML:TaggedValue tag="src_aggregation" value="0"/>
								<UML:TaggedValue tag="src_isOrdered" value="false"/>
								<UML:TaggedValue tag="src_isNavigable" value="false"/>
								<UML:TaggedValue tag="src_style" value="Owned=0;Navigable=Non-Navigable;"/>
								<UML:TaggedValue tag="dst_visibility" value="Public"/>
								<UML:TaggedValue tag="dst_aggregation" value="0"/>
								<UML:TaggedValue tag="dst_isOrdered" value="false"/>
								<UML:TaggedValue tag="dst_isNavigable" value="false"/>
								<UML:TaggedValue tag="dst_style" value="Owned=0;Navigable=Navigable;"/>
								<UML:TaggedValue tag="virtualInheritance" value="0"/>
								<UML:TaggedValue tag="mb" value=" &#xA;쳃mport"/>
							</UML:ModelElement.taggedValue>
						</UML:Dependency>
						<UML:Package name="ISO 19103 Edition 1 XML" xmi.id="EAPK_8339FE1D_E6C1_430f_87EA_D3EB217A11EC" isRoot="false" isLeaf="false" isAbstract="false" visibility="public">
							<UML:ModelElement.taggedValue>
								<UML:TaggedValue tag="parent" value="EAPK_2184D109_9F23_4b03_863B_F722FFFF9D9A"/>
								<UML:TaggedValue tag="created" value="2015-04-22 11:41:07"/>
								<UML:TaggedValue tag="modified" value="2017-08-04 09:47:13"/>
								<UML:TaggedValue tag="iscontrolled" value="TRUE"/>
								<UML:TaggedValue tag="xmlpath" value="iso-19103\trunk\ISO 19103 2015 XML.xml"/>
								<UML:TaggedValue tag="lastloaddate" value="2017-08-04 09:44:18"/>
								<UML:TaggedValue tag="lastsavedate" value="2015-05-04 13:57:55"/>
								<UML:TaggedValue tag="version" value="2015"/>
								<UML:TaggedValue tag="isprotected" value="FALSE"/>
								<UML:TaggedValue tag="usedtd" value="FALSE"/>
								<UML:TaggedValue tag="owner" value="knjetl"/>
								<UML:TaggedValue tag="xmiver" value="Enterprise Architect XMI/UML 1.3"/>
								<UML:TaggedValue tag="logxml" value="FALSE"/>
								<UML:TaggedValue tag="tpos" value="1"/>
								<UML:TaggedValue tag="batchsave" value="0"/>
								<UML:TaggedValue tag="batchload" value="0"/>
								<UML:TaggedValue tag="packageFlags" value="Recurse=0;VCCFG=implementation-XML;"/>
								<UML:TaggedValue tag="savedasstub" value="true"/>
								<UML:TaggedValue tag="phase" value="1.0"/>
								<UML:TaggedValue tag="status" value="Implemented"/>
								<UML:TaggedValue tag="author" value="John"/>
								<UML:TaggedValue tag="alias" value="Conceptual schema language"/>
								<UML:TaggedValue tag="complexity" value="1"/>
								<UML:TaggedValue tag="ea_stype" value="Public"/>
							</UML:ModelElement.taggedValue>
						</UML:Package>
						<UML:Package name="ISO TS19103 Edition 1 XML" xmi.id="EAPK_31591D82_13F0_4687_BC11_BEDFBCEB9772" isRoot="false" isLeaf="false" isAbstract="false" visibility="public">
							<UML:ModelElement.taggedValue>
								<UML:TaggedValue tag="documentation" value="import from Harmonized model with strip GUIDS 2014-07-10"/>
								<UML:TaggedValue tag="parent" value="EAPK_2184D109_9F23_4b03_863B_F722FFFF9D9A"/>
								<UML:TaggedValue tag="created" value="2008-04-17 08:46:36"/>
								<UML:TaggedValue tag="modified" value="2017-08-04 09:48:30"/>
								<UML:TaggedValue tag="iscontrolled" value="TRUE"/>
								<UML:TaggedValue tag="xmlpath" value="iso-19103\trunk\ISO 19103 2005 XML.xml"/>
								<UML:TaggedValue tag="lastloaddate" value="2017-08-04 09:44:05"/>
								<UML:TaggedValue tag="lastsavedate" value="2008-04-17 08:46:36"/>
								<UML:TaggedValue tag="version" value="1.0."/>
								<UML:TaggedValue tag="isprotected" value="FALSE"/>
								<UML:TaggedValue tag="usedtd" value="FALSE"/>
								<UML:TaggedValue tag="owner" value="knjetl"/>
								<UML:TaggedValue tag="xmiver" value="Enterprise Architect XMI/UML 1.3"/>
								<UML:TaggedValue tag="logxml" value="FALSE"/>
								<UML:TaggedValue tag="tpos" value="2"/>
								<UML:TaggedValue tag="batchsave" value="0"/>
								<UML:TaggedValue tag="batchload" value="0"/>
								<UML:TaggedValue tag="packageFlags" value="Recurse=0;VCCFG=implementation-XML;"/>
								<UML:TaggedValue tag="savedasstub" value="true"/>
								<UML:TaggedValue tag="alias" value="Conceptual schema language"/>
								<UML:TaggedValue tag="complexity" value="1"/>
								<UML:TaggedValue tag="ea_stype" value="Public"/>
							</UML:ModelElement.taggedValue>
						</UML:Package>
					</UML:Namespace.ownedElement>
				</UML:Package>
			</UML:Namespace.ownedElement>
		</UML:Model>
		<UML:TaggedValue tag="edition" xmi.id="EAID_56F30E85_B48D_41cb_A200_0218D0FD3E32" modelElement="MX_EAID_2184D109_9F23_4b03_863B_F722FFFF9D9A"/>
		<UML:TaggedValue tag="name" xmi.id="EAID_875A55CE_043A_4790_B728_15D5D46D0DBD" value="Conceptual schema language" modelElement="MX_EAID_2184D109_9F23_4b03_863B_F722FFFF9D9A"/>
		<UML:TaggedValue tag="number" xmi.id="EAID_FAE99682_C5A1_4e53_A692_C22FBBA39374" value="19103" modelElement="MX_EAID_2184D109_9F23_4b03_863B_F722FFFF9D9A"/>
		<UML:TaggedValue tag="publicationDate" xmi.id="EAID_8FFC1D8C_EE27_434c_9FDF_F4F2BCD24B6A" modelElement="MX_EAID_2184D109_9F23_4b03_863B_F722FFFF9D9A"/>
		<UML:TaggedValue tag="yearVersion" xmi.id="EAID_63754636_9BBC_4a33_83EC_1D494CABFBBA" modelElement="MX_EAID_2184D109_9F23_4b03_863B_F722FFFF9D9A"/>
		<UML:TaggedValue tag="edition" xmi.id="EAID_FCFE3A79_F909_4d26_A002_92C0D261798A" value="1" modelElement="EAID_31591D82_13F0_4687_BC11_BEDFBCEB9772"/>
		<UML:TaggedValue tag="isApplicationSchema" xmi.id="EAID_44F7871D_1E35_4f02_8310_97E2131720AC" value="true" modelElement="EAID_31591D82_13F0_4687_BC11_BEDFBCEB9772"/>
		<UML:TaggedValue tag="name" xmi.id="EAID_A98C4B45_3F6F_4270_BB39_339CBFA63034" value="Conceptual schema language" modelElement="EAID_31591D82_13F0_4687_BC11_BEDFBCEB9772"/>
		<UML:TaggedValue tag="number" xmi.id="EAID_D4C01A96_F3D1_459d_833D_2DE858D6F778" value="TS19103" modelElement="EAID_31591D82_13F0_4687_BC11_BEDFBCEB9772"/>
		<UML:TaggedValue tag="publicationDate" xmi.id="EAID_A9E265EB_ADB0_4540_BA40_A19B93437213" value="2005-07" modelElement="EAID_31591D82_13F0_4687_BC11_BEDFBCEB9772"/>
		<UML:TaggedValue tag="yearVersion" xmi.id="EAID_DE9DD6F3_2AE1_4512_A53B_EDEA2DBECB5D" value="2005" modelElement="EAID_31591D82_13F0_4687_BC11_BEDFBCEB9772"/>
		<UML:TaggedValue tag="edition" xmi.id="EAID_D8C238B3_EF41_4ffa_8958_3CFA20F300DF" value="1" modelElement="EAID_8339FE1D_E6C1_430f_87EA_D3EB217A11EC"/>
		<UML:TaggedValue tag="name" xmi.id="EAID_E7576E9A_CDB1_469d_AC42_68C8D22E98CB" value="Conceptual schema language" modelElement="EAID_8339FE1D_E6C1_430f_87EA_D3EB217A11EC"/>
		<UML:TaggedValue tag="number" xmi.id="EAID_F783A096_199B_4477_B0FA_F36FC12E1361" value="19103" modelElement="EAID_8339FE1D_E6C1_430f_87EA_D3EB217A11EC"/>
		<UML:TaggedValue tag="publicationDate" xmi.id="EAID_FE871E55_165E_416b_A707_C0B314D807FC" value="2015-12" modelElement="EAID_8339FE1D_E6C1_430f_87EA_D3EB217A11EC"/>
		<UML:TaggedValue tag="yearVersion" xmi.id="EAID_495CB4A5_4285_4742_A415_049AF3648462" value="2015" modelElement="EAID_8339FE1D_E6C1_430f_87EA_D3EB217A11EC"/>
		<UML:DiagramElement geometry="Left=27;Top=67;Right=254;Bottom=147;" subject="EAID_31591D82_13F0_4687_BC11_BEDFBCEB9772" seqno="2" style="DUID=1107313A;">
			<UML:ModelElement.taggedValue>
				<UML:TaggedValue tag="diagram_guid" value="EAID_B6BDAF20_D649_4100_BC0E_7DDEE499B51C"/>
			</UML:ModelElement.taggedValue>
		</UML:DiagramElement>
		<UML:DiagramElement geometry="Left=622;Top=51;Right=849;Bottom=131;" subject="EAID_31591D82_13F0_4687_BC11_BEDFBCEB9772" seqno="9" style="DUID=F46EDB3A;">
			<UML:ModelElement.taggedValue>
				<UML:TaggedValue tag="diagram_guid" value="EAID_0820028F_C85F_46b1_AB7C_7098D228A209"/>
			</UML:ModelElement.taggedValue>
		</UML:DiagramElement>
		<UML:DiagramElement geometry="Left=46;Top=140;Right=273;Bottom=220;" subject="EAID_31591D82_13F0_4687_BC11_BEDFBCEB9772" seqno="5" style="DUID=480486BD;">
			<UML:ModelElement.taggedValue>
				<UML:TaggedValue tag="diagram_guid" value="EAID_AD3A12A8_0513_44cc_8A96_4E258A749E43"/>
			</UML:ModelElement.taggedValue>
		</UML:DiagramElement>
		<UML:DiagramElement geometry="Left=294;Top=209;Right=521;Bottom=289;" subject="EAID_31591D82_13F0_4687_BC11_BEDFBCEB9772" seqno="3" style="DUID=58F7F3F6;">
			<UML:ModelElement.taggedValue>
				<UML:TaggedValue tag="diagram_guid" value="EAID_A3057485_5383_461b_B4C0_8AB123443816"/>
			</UML:ModelElement.taggedValue>
		</UML:DiagramElement>
		<UML:DiagramElement geometry="Left=235;Top=116;Right=462;Bottom=196;" subject="EAID_31591D82_13F0_4687_BC11_BEDFBCEB9772" seqno="3" style="DUID=9ADFF47F;">
			<UML:ModelElement.taggedValue>
				<UML:TaggedValue tag="diagram_guid" value="EAID_0EBAA9E9_DF3E_4c1e_A02A_56F48B73A43E"/>
			</UML:ModelElement.taggedValue>
		</UML:DiagramElement>
		<UML:DiagramElement geometry="Left=493;Top=299;Right=720;Bottom=379;" subject="EAID_31591D82_13F0_4687_BC11_BEDFBCEB9772" seqno="4" style="DUID=16374794;">
			<UML:ModelElement.taggedValue>
				<UML:TaggedValue tag="diagram_guid" value="EAID_4AFC75DA_21EA_492b_8543_35319BBCA8DA"/>
			</UML:ModelElement.taggedValue>
		</UML:DiagramElement>
		<UML:DiagramElement geometry="Left=511;Top=263;Right=738;Bottom=343;" subject="EAID_31591D82_13F0_4687_BC11_BEDFBCEB9772" seqno="1" style="DUID=8169D504;">
			<UML:ModelElement.taggedValue>
				<UML:TaggedValue tag="diagram_guid" value="EAID_10097026_2662_44fa_8529_CF35AF1AB9C9"/>
			</UML:ModelElement.taggedValue>
		</UML:DiagramElement>
		<UML:DiagramElement geometry="SX=0;SY=0;EX=0;EY=0;" subject="EAID_04AA1765_B582_4465_ADFA_6793F4F08837" style=";">
			<UML:ModelElement.taggedValue>
				<UML:TaggedValue tag="diagram_guid" value="EAID_0EBAA9E9_DF3E_4c1e_A02A_56F48B73A43E"/>
				<UML:TaggedValue tag="hidden" value="0"/>
			</UML:ModelElement.taggedValue>
		</UML:DiagramElement>
		<UML:DiagramElement geometry="SX=0;SY=0;EX=0;EY=0;" subject="EAID_04AA1765_B582_4465_ADFA_6793F4F08837" style=";">
			<UML:ModelElement.taggedValue>
				<UML:TaggedValue tag="diagram_guid" value="EAID_AD3A12A8_0513_44cc_8A96_4E258A749E43"/>
				<UML:TaggedValue tag="hidden" value="0"/>
			</UML:ModelElement.taggedValue>
		</UML:DiagramElement>
		<UML:DiagramElement geometry="SX=0;SY=0;EX=0;EY=0;" subject="EAID_04AA1765_B582_4465_ADFA_6793F4F08837" style=";">
			<UML:ModelElement.taggedValue>
				<UML:TaggedValue tag="diagram_guid" value="EAID_0820028F_C85F_46b1_AB7C_7098D228A209"/>
				<UML:TaggedValue tag="hidden" value="0"/>
			</UML:ModelElement.taggedValue>
		</UML:DiagramElement>
		<UML:DiagramElement geometry="SX=0;SY=0;EX=0;EY=0;" subject="EAID_04AA1765_B582_4465_ADFA_6793F4F08837" style=";">
			<UML:ModelElement.taggedValue>
				<UML:TaggedValue tag="diagram_guid" value="EAID_B6BDAF20_D649_4100_BC0E_7DDEE499B51C"/>
				<UML:TaggedValue tag="hidden" value="0"/>
			</UML:ModelElement.taggedValue>
		</UML:DiagramElement>
		<UML:DiagramElement geometry="SX=0;SY=0;EX=0;EY=0;" subject="EAID_04AA1765_B582_4465_ADFA_6793F4F08837" style=";">
			<UML:ModelElement.taggedValue>
				<UML:TaggedValue tag="diagram_guid" value="EAID_A3057485_5383_461b_B4C0_8AB123443816"/>
				<UML:TaggedValue tag="hidden" value="0"/>
			</UML:ModelElement.taggedValue>
		</UML:DiagramElement>
		<UML:DiagramElement geometry="SX=0;SY=0;EX=0;EY=0;EDGE=1;$LLB=;LLT=;LMT=;LMB=;LRT=;LRB=;IRHS=;ILHS=;" subject="EAID_04AA1765_B582_4465_ADFA_6793F4F08837" style="Mode=3;EOID=8169D504;SOID=19DD2162;Color=-1;LWidth=0;">
			<UML:ModelElement.taggedValue>
				<UML:TaggedValue tag="diagram_guid" value="EAID_10097026_2662_44fa_8529_CF35AF1AB9C9"/>
				<UML:TaggedValue tag="hidden" value="255"/>
			</UML:ModelElement.taggedValue>
		</UML:DiagramElement>
		<UML:DiagramElement geometry="SX=0;SY=0;EX=0;EY=0;EDGE=1;$LLB=;LLT=;LMT=;LMB=;LRT=;LRB=;IRHS=;ILHS=;" subject="EAID_04AA1765_B582_4465_ADFA_6793F4F08837" style="Mode=3;EOID=16374794;SOID=09DD936C;Color=-1;LWidth=0;">
			<UML:ModelElement.taggedValue>
				<UML:TaggedValue tag="diagram_guid" value="EAID_4AFC75DA_21EA_492b_8543_35319BBCA8DA"/>
				<UML:TaggedValue tag="hidden" value="255"/>
			</UML:ModelElement.taggedValue>
		</UML:DiagramElement>
		<UML:DiagramElement geometry="SX=0;SY=0;EX=0;EY=0;" subject="EAID_5D8F12B3_5393_4b04_A635_23493F611ADC" style=";">
			<UML:ModelElement.taggedValue>
				<UML:TaggedValue tag="diagram_guid" value="EAID_0820028F_C85F_46b1_AB7C_7098D228A209"/>
				<UML:TaggedValue tag="hidden" value="0"/>
			</UML:ModelElement.taggedValue>
		</UML:DiagramElement>
		<UML:DiagramElement geometry="SX=0;SY=0;EX=0;EY=0;" subject="EAID_6546CD33_9C54_4d57_9876_040519502525" style=";">
			<UML:ModelElement.taggedValue>
				<UML:TaggedValue tag="diagram_guid" value="EAID_0EBAA9E9_DF3E_4c1e_A02A_56F48B73A43E"/>
				<UML:TaggedValue tag="hidden" value="0"/>
			</UML:ModelElement.taggedValue>
		</UML:DiagramElement>
		<UML:DiagramElement geometry="SX=0;SY=0;EX=0;EY=0;" subject="EAID_9F27D3AB_B280_4adc_9910_63120BEB676E" style=";">
			<UML:ModelElement.taggedValue>
				<UML:TaggedValue tag="diagram_guid" value="EAID_4AFC75DA_21EA_492b_8543_35319BBCA8DA"/>
				<UML:TaggedValue tag="hidden" value="0"/>
			</UML:ModelElement.taggedValue>
		</UML:DiagramElement>
		<UML:DiagramElement geometry="SX=68;SY=-9;EX=-67;EY=-39;EDGE=2;$LLB=;LLT=;LMT=;LMB=CX=42:CY=13:OX=0:OY=0:HDN=0:BLD=0:ITA=0:UND=0:CLR=-1:ALN=0:DIR=0:ROT=0;LRT=;LRB=;IRHS=;ILHS=;" subject="EAID_AD51F969_76E8_4f7c_A46D_C3B2C48A0EA6" style="Mode=3;EOID=8169D504;SOID=7A9313BD;Color=-1;LWidth=0;">
			<UML:ModelElement.taggedValue>
				<UML:TaggedValue tag="diagram_guid" value="EAID_10097026_2662_44fa_8529_CF35AF1AB9C9"/>
				<UML:TaggedValue tag="hidden" value="0"/>
				<UML:TaggedValue tag="path" value="529:-431;"/>
			</UML:ModelElement.taggedValue>
		</UML:DiagramElement>
		<UML:DiagramElement geometry="SX=0;SY=0;EX=0;EY=0;" subject="EAID_AD5DBBA9_BB64_4016_B091_DBF7CEA65AEB" style=";">
			<UML:ModelElement.taggedValue>
				<UML:TaggedValue tag="diagram_guid" value="EAID_AD3A12A8_0513_44cc_8A96_4E258A749E43"/>
				<UML:TaggedValue tag="hidden" value="0"/>
			</UML:ModelElement.taggedValue>
		</UML:DiagramElement>
		<UML:DiagramElement geometry="SX=0;SY=0;EX=0;EY=0;" subject="EAID_C6BAA895_7390_42f4_85BE_ED73833A87F0" style=";">
			<UML:ModelElement.taggedValue>
				<UML:TaggedValue tag="diagram_guid" value="EAID_A3057485_5383_461b_B4C0_8AB123443816"/>
				<UML:TaggedValue tag="hidden" value="0"/>
			</UML:ModelElement.taggedValue>
		</UML:DiagramElement>
		<UML:DiagramElement geometry="SX=0;SY=0;EX=0;EY=0;" subject="EAID_04AA1765_B582_4465_ADFA_6793F4F08837" style=";">
			<UML:ModelElement.taggedValue>
				<UML:TaggedValue tag="diagram_guid" value="EAID_0EBAA9E9_DF3E_4c1e_A02A_56F48B73A43E"/>
				<UML:TaggedValue tag="hidden" value="0"/>
			</UML:ModelElement.taggedValue>
		</UML:DiagramElement>
		<UML:DiagramElement geometry="SX=0;SY=0;EX=0;EY=0;" subject="EAID_04AA1765_B582_4465_ADFA_6793F4F08837" style=";">
			<UML:ModelElement.taggedValue>
				<UML:TaggedValue tag="diagram_guid" value="EAID_AD3A12A8_0513_44cc_8A96_4E258A749E43"/>
				<UML:TaggedValue tag="hidden" value="0"/>
			</UML:ModelElement.taggedValue>
		</UML:DiagramElement>
		<UML:DiagramElement geometry="SX=0;SY=0;EX=0;EY=0;" subject="EAID_04AA1765_B582_4465_ADFA_6793F4F08837" style=";">
			<UML:ModelElement.taggedValue>
				<UML:TaggedValue tag="diagram_guid" value="EAID_0820028F_C85F_46b1_AB7C_7098D228A209"/>
				<UML:TaggedValue tag="hidden" value="0"/>
			</UML:ModelElement.taggedValue>
		</UML:DiagramElement>
		<UML:DiagramElement geometry="SX=0;SY=0;EX=0;EY=0;" subject="EAID_04AA1765_B582_4465_ADFA_6793F4F08837" style=";">
			<UML:ModelElement.taggedValue>
				<UML:TaggedValue tag="diagram_guid" value="EAID_B6BDAF20_D649_4100_BC0E_7DDEE499B51C"/>
				<UML:TaggedValue tag="hidden" value="0"/>
			</UML:ModelElement.taggedValue>
		</UML:DiagramElement>
		<UML:DiagramElement geometry="SX=0;SY=0;EX=0;EY=0;" subject="EAID_04AA1765_B582_4465_ADFA_6793F4F08837" style=";">
			<UML:ModelElement.taggedValue>
				<UML:TaggedValue tag="diagram_guid" value="EAID_A3057485_5383_461b_B4C0_8AB123443816"/>
				<UML:TaggedValue tag="hidden" value="0"/>
			</UML:ModelElement.taggedValue>
		</UML:DiagramElement>
		<UML:DiagramElement geometry="SX=0;SY=0;EX=0;EY=0;EDGE=1;$LLB=;LLT=;LMT=;LMB=;LRT=;LRB=;IRHS=;ILHS=;" subject="EAID_04AA1765_B582_4465_ADFA_6793F4F08837" style="Mode=3;EOID=8169D504;SOID=19DD2162;Color=-1;LWidth=0;">
			<UML:ModelElement.taggedValue>
				<UML:TaggedValue tag="diagram_guid" value="EAID_10097026_2662_44fa_8529_CF35AF1AB9C9"/>
				<UML:TaggedValue tag="hidden" value="255"/>
			</UML:ModelElement.taggedValue>
		</UML:DiagramElement>
		<UML:DiagramElement geometry="SX=0;SY=0;EX=0;EY=0;EDGE=1;$LLB=;LLT=;LMT=;LMB=;LRT=;LRB=;IRHS=;ILHS=;" subject="EAID_04AA1765_B582_4465_ADFA_6793F4F08837" style="Mode=3;EOID=16374794;SOID=09DD936C;Color=-1;LWidth=0;">
			<UML:ModelElement.taggedValue>
				<UML:TaggedValue tag="diagram_guid" value="EAID_4AFC75DA_21EA_492b_8543_35319BBCA8DA"/>
				<UML:TaggedValue tag="hidden" value="255"/>
			</UML:ModelElement.taggedValue>
		</UML:DiagramElement>
		<UML:DiagramElement geometry="SX=0;SY=0;EX=0;EY=0;" subject="EAID_5D8F12B3_5393_4b04_A635_23493F611ADC" style=";">
			<UML:ModelElement.taggedValue>
				<UML:TaggedValue tag="diagram_guid" value="EAID_0820028F_C85F_46b1_AB7C_7098D228A209"/>
				<UML:TaggedValue tag="hidden" value="0"/>
			</UML:ModelElement.taggedValue>
		</UML:DiagramElement>
		<UML:DiagramElement geometry="SX=0;SY=0;EX=0;EY=0;" subject="EAID_6546CD33_9C54_4d57_9876_040519502525" style=";">
			<UML:ModelElement.taggedValue>
				<UML:TaggedValue tag="diagram_guid" value="EAID_0EBAA9E9_DF3E_4c1e_A02A_56F48B73A43E"/>
				<UML:TaggedValue tag="hidden" value="0"/>
			</UML:ModelElement.taggedValue>
		</UML:DiagramElement>
		<UML:DiagramElement geometry="SX=0;SY=0;EX=0;EY=0;" subject="EAID_9F27D3AB_B280_4adc_9910_63120BEB676E" style=";">
			<UML:ModelElement.taggedValue>
				<UML:TaggedValue tag="diagram_guid" value="EAID_4AFC75DA_21EA_492b_8543_35319BBCA8DA"/>
				<UML:TaggedValue tag="hidden" value="0"/>
			</UML:ModelElement.taggedValue>
		</UML:DiagramElement>
		<UML:DiagramElement geometry="SX=68;SY=-9;EX=-67;EY=-39;EDGE=2;$LLB=;LLT=;LMT=;LMB=CX=42:CY=13:OX=0:OY=0:HDN=0:BLD=0:ITA=0:UND=0:CLR=-1:ALN=0:DIR=0:ROT=0;LRT=;LRB=;IRHS=;ILHS=;" subject="EAID_AD51F969_76E8_4f7c_A46D_C3B2C48A0EA6" style="Mode=3;EOID=8169D504;SOID=7A9313BD;Color=-1;LWidth=0;">
			<UML:ModelElement.taggedValue>
				<UML:TaggedValue tag="diagram_guid" value="EAID_10097026_2662_44fa_8529_CF35AF1AB9C9"/>
				<UML:TaggedValue tag="hidden" value="0"/>
				<UML:TaggedValue tag="path" value="529:-431;"/>
			</UML:ModelElement.taggedValue>
		</UML:DiagramElement>
		<UML:DiagramElement geometry="SX=0;SY=0;EX=0;EY=0;" subject="EAID_AD5DBBA9_BB64_4016_B091_DBF7CEA65AEB" style=";">
			<UML:ModelElement.taggedValue>
				<UML:TaggedValue tag="diagram_guid" value="EAID_AD3A12A8_0513_44cc_8A96_4E258A749E43"/>
				<UML:TaggedValue tag="hidden" value="0"/>
			</UML:ModelElement.taggedValue>
		</UML:DiagramElement>
		<UML:DiagramElement geometry="SX=0;SY=0;EX=0;EY=0;" subject="EAID_C6BAA895_7390_42f4_85BE_ED73833A87F0" style=";">
			<UML:ModelElement.taggedValue>
				<UML:TaggedValue tag="diagram_guid" value="EAID_A3057485_5383_461b_B4C0_8AB123443816"/>
				<UML:TaggedValue tag="hidden" value="0"/>
			</UML:ModelElement.taggedValue>
		</UML:DiagramElement>
	</XMI.content>
	<XMI.difference/>
	<XMI.extensions xmi.extender="Enterprise Architect 2.5">
		<EAStub xmi.id="EAPK_DC9F3A84_5D39_4092_AADF_860E89E61B89" name="Metadata Common Classes" UMLType="Package"/>
		<EAStub xmi.id="EAPK_19EE7D8E_DC0C_42d9_B272_E478A5F95291" name="Metadata base" UMLType="Package"/>
		<EAStub xmi.id="EAPK_CC8F3DBB_4765_419f_BDEF_7080D866A3E8" name="Metadata for Distribution" UMLType="Package"/>
		<EAStub xmi.id="EAPK_9A048FF7_4C59_44aa_BABE_1B180DE058AF" name="Procedures for registration" UMLType="Package"/>
		<EAStub xmi.id="EAPK_A1EEA4B8_12F2_434d_BAEF_3C6AA7800EDD" name="Data quality" UMLType="Package"/>
		<EAStub xmi.id="EAPK_757D8C16_2C34_47c8_B7A5_FC55871A4D53" name="Feature Catalogue" UMLType="Package"/>
		<EAStub xmi.id="EAPK_5AC9C40D_B36F_4a1b_B66C_BBA035747259" name="Metadata for Acquisition" UMLType="Package"/>
		<EAStub xmi.id="EAPK_9CADA801_6694_4944_90FB_93A9CB976661" name="Metadata for Lineage" UMLType="Package"/>
		<EAStub xmi.id="EAPK_1D0C3864_B566_447c_A51E_52AE73A7737D" name="Metadata for Constraints" UMLType="Package"/>
	</XMI.extensions>
</XMI>
